extended_data_types/__init__.py
extended_data_types/base64_utils.py
extended_data_types/export_utils.py
extended_data_types/file_data_type.py
extended_data_types/hcl2_utils.py
extended_data_types/import_utils.py
extended_data_types/json_utils.py
extended_data_types/list_data_type.py
extended_data_types/map_data_type.py
extended_data_types/matcher_utils.py
extended_data_types/number_transformations.py
extended_data_types/py.typed
extended_data_types/splitter_utils.py
extended_data_types/stack_utils.py
extended_data_types/state_utils.py
extended_data_types/string_data_type.py
extended_data_types/string_transformations.py
extended_data_types/toml_utils.py
extended_data_types/type_utils.py
extended_data_types/transformations/__init__.py
extended_data_types/transformations/numbers/__init__.py
extended_data_types/transformations/numbers/notation.py
extended_data_types/transformations/numbers/words.py
extended_data_types/transformations/strings/__init__.py
extended_data_types/transformations/strings/inflection.py
extended_data_types/yaml_utils/__init__.py
extended_data_types/yaml_utils/constructors.py
extended_data_types/yaml_utils/dumpers.py
extended_data_types/yaml_utils/loaders.py
extended_data_types/yaml_utils/representers.py
extended_data_types/yaml_utils/tag_classes.py
extended_data_types/yaml_utils/utils.py
extended_data_types-5.2.1.dist-info/METADATA
extended_data_types-5.2.1.dist-info/WHEEL
extended_data_types-5.2.1.dist-info/RECORD
