Metadata-Version: 2.4
Name: extended-data-types
Version: 5.2.1
Summary: Extended functionality for data types
Project-URL: Documentation, https://github.com/jbcom/extended-data-types#readme
Project-URL: Issues, https://github.com/jbcom/extended-data-types/issues
Project-URL: Source, https://github.com/jbcom/extended-data-types
Author-email: Jon Bogaty <jon@jonbogaty.com>
Maintainer-email: Jon Bogaty <jon@jonbogaty.com>
License: MIT
Keywords: data-types,python3,utilities
Classifier: Development Status :: 5 - Production/Stable
Classifier: Intended Audience :: Developers
Classifier: License :: OSI Approved :: MIT License
Classifier: Programming Language :: Python :: 3
Classifier: Programming Language :: Python :: 3.9
Classifier: Programming Language :: Python :: 3.10
Classifier: Programming Language :: Python :: 3.11
Classifier: Programming Language :: Python :: 3.12
Classifier: Programming Language :: Python :: 3.13
Classifier: Typing :: Typed
Requires-Python: >=3.9
Requires-Dist: deepmerge>=2.0
Requires-Dist: gitpython>=3.1.0
Requires-Dist: inflection>=0.5.1
Requires-Dist: num2words>=0.5.14
Requires-Dist: orjson>=3.10.7
Requires-Dist: python-hcl2>=4.3.4
Requires-Dist: pyyaml>=6.0.1
Requires-Dist: ruamel-yaml>=0.18.0
Requires-Dist: sortedcontainers>=2.4.0
Requires-Dist: tomlkit>=0.13.2
Requires-Dist: typing-extensions>=4.3.0; python_version < '3.10'
Requires-Dist: validators>=0.22.0
Requires-Dist: wrapt>=1.16.0
Provides-Extra: docs
Requires-Dist: docutils>=0.17; extra == 'docs'
Requires-Dist: myst-parser>=3.0.1; extra == 'docs'
Requires-Dist: sphinx-autodoc2>=0.5.0; extra == 'docs'
Requires-Dist: sphinx>=7.0; extra == 'docs'
Requires-Dist: sphinxawesome-theme>=5.2.0; extra == 'docs'
Provides-Extra: tests
Requires-Dist: coverage[toml]>=7.6.0; extra == 'tests'
Requires-Dist: pytest-cov>=5.0.0; extra == 'tests'
Requires-Dist: pytest-mock>=3.14.0; extra == 'tests'
Requires-Dist: pytest-xdist>=3.6.1; extra == 'tests'
Requires-Dist: pytest>=8.2.2; extra == 'tests'
Provides-Extra: typing
Requires-Dist: mypy>=1.0.0; extra == 'typing'
Requires-Dist: sortedcontainers-stubs>=2.4.2; extra == 'typing'
Requires-Dist: types-pyyaml>=6.0.12.20240724; extra == 'typing'
